Metadata-Version: 1.0
Name: py8fact
Version: 0.1.1
Summary: random facts
Home-page: https://github.com/OpenJarbas/8fact
Author: jarbasAI
Author-email: jarbasai@mailfence.com
License: Apache2.0
Platform: UNKNOWN
